demotron/__init__.py
demotron/config.py
demotron/load_raw_events.py
demotron/main.py
demotron/rename_column_util.py
demotron/tests/__init__.py
demotron/tests/test_config.py
demotron/tests/test_integration.py
demotron/tests/test_load_raw_events.py
demotron/tests/test_main.py
demotron/tests/test_rename_column_util.py
demotron-0.1.1.dist-info/LICENSE
demotron-0.1.1.dist-info/METADATA
demotron-0.1.1.dist-info/WHEEL
demotron-0.1.1.dist-info/entry_points.txt
demotron-0.1.1.dist-info/RECORD
