Metadata-Version: 2.1
Name: demotron
Version: 0.1.1
Summary: CLI to delight real people with live demos
Author: Sung Won Chung
Author-email: sungwonchung3@gmail.com
Requires-Python: >=3.12,<4.0
Classifier: Programming Language :: Python :: 3
Classifier: Programming Language :: Python :: 3.12
Requires-Dist: google-auth (>=2.32.0,<3.0.0)
Requires-Dist: sqlmesh[bigquery,web] (==0.107.6)
Requires-Dist: typer[all] (>=0.12.3,<0.13.0)
